{
  "assetsByChunkName": {
    "vendors~app-account~app-confirmation~app-order": "chunk.317302bbb90b4c9e9791.js",
    "vendors~app-account~app-checkout": "chunk.3a95a56339a83b2d4af4.js",
    "vendors~app-cart~app-checkout": "chunk.dc8c81e9a3330640348c.js",
    "admin": [
      "admin.ab9be2b328a62a5151a6.js",
      "admin.ab9be2b328a62a5151a6.js.map"
    ],
    "app-account": "chunk.c676243b70b5425abe29.js",
    "app-confirmation": "chunk.7812bb53193959d0d435.js",
    "app-order": "chunk.be94ad88b22cb81c8496.js",
    "checkout": [
      "checkout.3858fa62812a2c23dd53.js",
      "checkout.3858fa62812a2c23dd53.js.map"
    ],
    "storefront": [
      "storefront.e5a3dd596419a2b934c4.css",
      "storefront.e4b41d5f2f1315849a3d.js",
      "storefront.e5a3dd596419a2b934c4.css.map",
      "storefront.e4b41d5f2f1315849a3d.js.map"
    ],
    "vendors~app-cart": "chunk.821797cbd50d05a2896c.js",
    "vendors~app-checkout": "chunk.2997cb442115260423fe.js"
  }
}